dynarag/__init__.py
dynarag/constants.py
dynarag/exceptions.py
dynarag/main.py
dynarag-0.1.0.dist-info/METADATA
dynarag-0.1.0.dist-info/WHEEL
dynarag-0.1.0.dist-info/RECORD
