Metadata-Version: 2.1
Name: dynarag
Version: 0.1.0
Summary: Python client to the DynaRAG API
Author: Frederick Mannings
Author-email: fred.mannings@predixus.com
Requires-Python: >=3.9,<4.0
Classifier: Programming Language :: Python :: 3
Classifier: Programming Language :: Python :: 3.9
Classifier: Programming Language :: Python :: 3.10
Classifier: Programming Language :: Python :: 3.11
Classifier: Programming Language :: Python :: 3.12
Classifier: Programming Language :: Python :: 3.13
